confluence_markdown_exporter/__init__.py
confluence_markdown_exporter/confluence.py
confluence_markdown_exporter/main.py
confluence_markdown_exporter/utils/__init__.py
confluence_markdown_exporter/utils/export.py
confluence_markdown_exporter/utils/measure_time.py
confluence_markdown_exporter/utils/table_converter.py
confluence_markdown_exporter_advanced-0.5.0.dist-info/licenses/LICENSE
confluence_markdown_exporter_advanced-0.5.0.dist-info/METADATA
confluence_markdown_exporter_advanced-0.5.0.dist-info/WHEEL
confluence_markdown_exporter_advanced-0.5.0.dist-info/entry_points.txt
confluence_markdown_exporter_advanced-0.5.0.dist-info/top_level.txt
confluence_markdown_exporter_advanced-0.5.0.dist-info/RECORD
