Metadata-Version: 2.4
Name: confluence-markdown-exporter-advanced
Version: 0.5.0
Summary: A tool to export Confluence pages to Markdown
Author: Forked by Max Ramer, original author Sebastian Penhouet
License: MIT
Project-URL: Homepage, https://github.com/mjramer/confluence-markdown-exporter
Project-URL: Documentation, https://github.com/mjramer/confluence-markdown-exporter/blob/main/README.md
Project-URL: Source, https://github.com/mjramer/confluence-markdown-exporter
Project-URL: Tracker, https://github.com/mjramer/confluence-markdown-exporter/issues
Keywords: confluence,atlassian,markdown,export,convertion,download
Requires-Python: >=3.9
License-File: LICENSE
Requires-Dist: atlassian-python-api
Requires-Dist: markdownify
Requires-Dist: pandas
Requires-Dist: pydantic-settings
Requires-Dist: pyyaml
Requires-Dist: tabulate
Requires-Dist: tqdm
Requires-Dist: typer
Provides-Extra: dev
Requires-Dist: ruff==0.9.10; extra == "dev"
Requires-Dist: pipx; extra == "dev"
Dynamic: license-file
